Metadata-Version: 2.1
Name: cores-ft
Version: 0.2
Summary: Monitora frequencia e temperatuda dos cores da CPU
Home-page: https://github.com/HenriqueCCdA/cores_ft
Author: Henrique C. C. de Andrade
Author-email: henrique.ccda@gmail.com
License: MIT
Platform: Linux
Classifier: Development Status :: 2 - Pre-Alpha
Classifier: Environment :: Console
Classifier: License :: OSI Approved :: MIT License
Classifier: Operating System :: POSIX :: Linux
Classifier: Programming Language :: Python
